openagents/__init__.py
openagents/cli.py
openagents/agents/__init__.py
openagents/agents/collaborator_agent.py
openagents/agents/langchain_agent.py
openagents/agents/orchestrator.py
openagents/agents/project_echo_agent.py
openagents/agents/runner.py
openagents/agents/simple_agent.py
openagents/agents/simple_echo_agent.py
openagents/agents/simple_openai_agent.py
openagents/agents/worker_agent.py
openagents/config/__init__.py
openagents/config/globals.py
openagents/config/llm_configs.py
openagents/config/prompt_templates.py
openagents/core/__init__.py
openagents/core/a2a_registry.py
openagents/core/a2a_task_store.py
openagents/core/agent_identity.py
openagents/core/agent_manager.py
openagents/core/base_mod.py
openagents/core/base_mod_adapter.py
openagents/core/client.py
openagents/core/event_gateway.py
openagents/core/event_processor.py
openagents/core/mod_registry.py
openagents/core/network.py
openagents/core/secret_manager.py
openagents/core/system_commands.py
openagents/core/topology.py
openagents/core/workspace.py
openagents/core/workspace_manager.py
openagents/core/connectors/__init__.py
openagents/core/connectors/a2a_connector.py
openagents/core/connectors/base.py
openagents/core/connectors/grpc_connector.py
openagents/core/connectors/http_connector.py
openagents/core/connectors/websocket_connector.py
openagents/core/transports/__init__.py
openagents/core/transports/a2a.py
openagents/core/transports/base.py
openagents/core/transports/grpc.py
openagents/core/transports/http.py
openagents/core/transports/mcp.py
openagents/core/transports/websocket.py
openagents/launchers/__init__.py
openagents/launchers/discovery_connector.py
openagents/launchers/network_launcher.py
openagents/launchers/terminal_console.py
openagents/lms/__init__.py
openagents/lms/llm_log_reader.py
openagents/lms/llm_logger.py
openagents/lms/providers.py
openagents/models/__init__.py
openagents/models/a2a.py
openagents/models/agent_actions.py
openagents/models/agent_config.py
openagents-0.8.5.post6.dist-info/licenses/LICENSE
openagents-0.8.5.post6.dist-info/METADATA
openagents-0.8.5.post6.dist-info/WHEEL
openagents-0.8.5.post6.dist-info/entry_points.txt
openagents-0.8.5.post6.dist-info/top_level.txt
openagents-0.8.5.post6.dist-info/RECORD
