Metadata-Version: 2.4
Name: openagents
Version: 0.8.5.post6
Summary: A flexible framework for building multi-agent systems with customizable protocols
Home-page: https://github.com/bestagents/openagents
Author: OpenAgents Team
Author-email: OpenAgents Team <info@openagents.org>
License: Apache-2.0
Project-URL: Homepage, https://github.com/bestagents/openagents
Project-URL: Documentation, https://openagents.readthedocs.io
Project-URL: Repository, https://github.com/bestagents/openagents
Project-URL: Issues, https://github.com/bestagents/openagents/issues
Classifier: Development Status :: 3 - Alpha
Classifier: Intended Audience :: Developers
Classifier: License :: OSI Approved :: Apache Software License
Classifier: Programming Language :: Python :: 3
Classifier: Programming Language :: Python :: 3.8
Classifier: Programming Language :: Python :: 3.9
Classifier: Programming Language :: Python :: 3.10
Classifier: Programming Language :: Python :: 3.11
Classifier: Programming Language :: Python :: 3.12
Classifier: Topic :: Software Development :: Libraries :: Python Modules
Classifier: Topic :: Scientific/Engineering :: Artificial Intelligence
Classifier: Topic :: System :: Distributed Computing
Requires-Python: >=3.8
License-File: LICENSE
Requires-Dist: pydantic>=2.0.0
Requires-Dist: pyyaml>=6.0
Requires-Dist: typing-extensions>=4.4.0
Requires-Dist: packaging>=21.0
Requires-Dist: aiohttp>=3.9.0
Requires-Dist: websockets>=11.0
Requires-Dist: asyncio-throttle>=1.0.0
Requires-Dist: requests>=2.25.0
Requires-Dist: grpcio>=1.50.0
Requires-Dist: grpcio-tools>=1.50.0
Requires-Dist: cryptography>=40.0.0
Requires-Dist: pynacl>=1.5.0
Requires-Dist: click>=8.1.0
Requires-Dist: rich>=13.0.0
Requires-Dist: typer>=0.9.0
Requires-Dist: jinja2>=3.1.0
Requires-Dist: python-dotenv>=1.0.0
Requires-Dist: prometheus-client>=0.16.0
Requires-Dist: structlog>=23.0.0
Requires-Dist: mcp>=1.15.0
Requires-Dist: openai>=1.98
Provides-Extra: p2p
Requires-Dist: libp2p>=0.2.0; extra == "p2p"
Provides-Extra: webrtc
Requires-Dist: aiortc>=1.6.0; extra == "webrtc"
Provides-Extra: langchain
Requires-Dist: langchain>=0.2.0; extra == "langchain"
Requires-Dist: langchain-core>=0.2.0; extra == "langchain"
Requires-Dist: langchain-openai>=0.1.0; extra == "langchain"
Provides-Extra: dev
Requires-Dist: pytest>=7.4.0; extra == "dev"
Requires-Dist: pytest-asyncio>=0.21.0; extra == "dev"
Requires-Dist: pytest-cov>=4.1.0; extra == "dev"
Requires-Dist: pytest-mock>=3.11.0; extra == "dev"
Requires-Dist: pytest-xdist>=3.3.0; extra == "dev"
Requires-Dist: black>=23.7.0; extra == "dev"
Requires-Dist: flake8>=6.0.0; extra == "dev"
Requires-Dist: mypy>=1.5.0; extra == "dev"
Requires-Dist: pre-commit>=3.3.0; extra == "dev"
Requires-Dist: coverage>=7.3.0; extra == "dev"
Requires-Dist: ipython>=8.0.0; extra == "dev"
Requires-Dist: jupyter>=1.0.0; extra == "dev"
Provides-Extra: docs
Requires-Dist: mkdocs>=1.5.0; extra == "docs"
Requires-Dist: mkdocs-material>=9.2.0; extra == "docs"
Requires-Dist: mkdocs-mermaid2-plugin>=1.1.0; extra == "docs"
Requires-Dist: mkdocstrings[python]>=0.22.0; extra == "docs"
Provides-Extra: all
Requires-Dist: openagents[dev,docs,langchain,p2p,webrtc]; extra == "all"
Dynamic: license-file
